Workbook

Sheet Sheet1
A1: UsuariId | B1: ProdId | C1: Fons | D1: IdMov | E1: Data | F1: TipusMov | G1: Parts | H1: PreuPart | I1: Import | K1: PreuPartReal | L1: Dif
A2: 1 | B2: 10 | C2: Bolsa Tecnología y Telecomunicaciones FI | D2: 15 | E2: 36841 | F2: 0 | G2: 679.64 | H2: 22.99204 | I2: =G2*H2 -> 15626.31
A3: 1 | B3: 11 | C3: Total Return N Acc €-H1 | D3: 16 | E3: 41166 | F3: 0 | G3: 547.64513 | H3: 18.26 | I3: =G3*H3 -> 10000 | K3: =Sheet2!E2 -> 18.26 | L3: =IF(ROUND(H3-K3,2)=0,"",H3-K3) | N3: =Sheet2!C2 -> Templeton Global Ttl Ret N(acc)EUR-H1
A4: 1 | B4: 12 | C4: American Extended Alpha R USD Acc | D4: 32 | E4: 41166 | F4: 0 | G4: 5006.5079 | H4: 1.9974 | I4: =G4*H4 -> 9999.9989 | K4: =Sheet2!E3 -> 2 | L4: =IF(ROUND(H4-K4,2)=0,"",H4-K4) | N4: =Sheet2!C3 -> Threadneedle Amer Extnd Alpha Rtl AccUSD
A5: 1 | B5: 3 | C5: Asian Smaller Companies Fund | D5: 1 | E5: 41172 | F5: 0 | G5: 325.522 | H5: 30.719859 | I5: =G5*H5 -> 9999.99 | K5: =Sheet2!E4 -> 30.72 | L5: =IF(ROUND(H5-K5,2)=0,"",H5-K5) | N5: =Sheet2!C4 -> abrdnI-Asian Smaller Companies A Acc USD
A6: 1 | B6: 3 | C6: Asian Smaller Companies Fund | D6: 2 | E6: 41187 | F6: 0 | G6: 1267.688 | H6: 31.55349 | I6: =G6*H6 -> 39999.98 | K6: =Sheet2!E5 -> 31.55 | L6: =IF(ROUND(H6-K6,2)=0,"",H6-K6) | N6: =Sheet2!C5 -> abrdnI-Asian Smaller Companies A Acc USD
A7: 1 | B7: 14 | C7: Patrimoine A EUR Acc | D7: 35 | E7: 41201 | F7: 0 | G7: 21.84 | H7: 549.56456 | I7: =G7*H7 -> 12002.49 | L7: =IF(ROUND(H7-K7,2)=0,"",H7-K7) -> 549.56456
A8: 1 | B8: 11 | C8: Total Return N Acc €-H1 | D8: 17 | E8: 41377 | F8: 0 | G8: 1010.611 | H8: 19.789998 | I8: =G8*H8 -> 19999.99 | K8: =Sheet2!E6 -> 19.79 | L8: =IF(ROUND(H8-K8,2)=0,"",H8-K8) | N8: =Sheet2!C6 -> Templeton Global Ttl Ret N(acc)EUR-H1
A9: 1 | B9: 11 | C9: Total Return N Acc €-H1 | D9: 24 | E9: 41383 | F9: 0 | G9: 280.07 | H9: 19.679973 | I9: =G9*H9 -> 5511.77 | K9: =Sheet2!E7 -> 19.68 | L9: =IF(ROUND(H9-K9,2)=0,"",H9-K9) | N9: =Sheet2!C7 -> Templeton Global Ttl Ret N(acc)EUR-H1
A10: 1 | B10: 13 | C10: Indonesia Fund A-USD | D10: 34 | E10: 41385 | F10: 0 | G10: 394.85 | H10: 26.279093 | I10: =G10*H10 -> 10376.3 | K10: =Sheet2!E10 -> 26.28 | L10: =IF(ROUND(H10-K10,2)=0,"",H10-K10) | N10: =Sheet2!C10 -> Fidelity Indonesia A-Dis-USD
A11: 1 | B11: 3 | C11: Asian Smaller Companies Fund | D11: 3 | E11: 41410 | F11: 0 | G11: 522.374 | H11: 38.286783 | I11: =G11*H11 -> 20000.02 | K11: =Sheet2!E11 -> 38.29 | L11: =IF(ROUND(H11-K11,2)=0,"",H11-K11) | N11: =Sheet2!C11 -> abrdnI-Asian Smaller Companies A Acc USD
A12: 1 | B12: 5 | C12: DWS Deutschland LC | D12: 26 | E12: 41439 | F12: 0 | G12: 249.3471 | H12: 139.70999 | I12: =G12*H12 -> 34836.28 | K12: =Sheet2!E12 -> 139.71 | L12: =IF(ROUND(H12-K12,2)=0,"",H12-K12)
A13: 1 | B13: 6 | C13: Biotechnology C USD Acc | D13: 7 | E13: 41492 | F13: 0 | G13: 24.092 | H13: 250.44123 | I13: =G13*H13 -> 6033.63 | K13: =Sheet2!E17 -> 250.44 | L13: =IF(ROUND(H13-K13,2)=0,"",H13-K13) | N13: =Sheet2!C17 -> Candriam Eqs L Biotech C USD Cap
A14: 1 | B14: 1 | C14: Optimal Income A-H Grs Acc Hdg EUR | D14: 27 | E14: 41521 | F14: 0 | G14: 58.502 | H14: 17.093262 | I14: =G14*H14 -> 999.99 | K14: =Sheet2!E19 -> 17.09 | L14: =IF(ROUND(H14-K14,2)=0,"",H14-K14) | N14: =Sheet2!C19 -> M G Optimal Income Euro A-H Acc
A15: 1 | B15: 2 | C15: European Growth N Acc ? | D15: 37 | E15: 41534 | F15: 0 | G15: 76.746 | H15: 13.029995 | I15: =G15*H15 -> 1000 | K15: =Sheet2!E20 -> 13.03 | L15: =IF(ROUND(H15-K15,2)=0,"",H15-K15) | N15: =Sheet2!C20 -> Templeton European Opps N(acc)EUR
A16: 1 | B16: 4 | C16: Thailand A-USD | D16: 11 | E16: 41554 | F16: 0 | G16: 28.28 | H16: 35.357143 | I16: =G16*H16 -> 999.9 | K16: =Sheet2!E21 -> 35.36 | L16: =IF(ROUND(H16-K16,2)=0,"",H16-K16) | N16: =Sheet2!C21 -> Fidelity Thailand A-Dis-USD
A17: 1 | B17: 4 | C17: Thailand A-USD | D17: 12 | E17: 41565 | F17: 0 | G17: 134.86 | H17: 37.076301 | I17: =G17*H17 -> 5000.11 | K17: =Sheet2!E22 -> 37.08 | L17: =IF(ROUND(H17-K17,2)=0,"",H17-K17) | N17: =Sheet2!C22 -> Fidelity Thailand A-Dis-USD
A18: 1 | B18: 6 | C18: Biotechnology C USD Acc | D18: 39 | E18: 41673 | F18: 0 | G18: 3.144 | H18: 304.86641 | I18: =G18*H18 -> 958.5 | K18: =Sheet2!E23 -> 304.86 | L18: =IF(ROUND(H18-K18,2)=0,"",H18-K18) -> 0.0064122137 | M18: =L18*G18 -> 0.02016 | N18: =Sheet2!C23 -> Candriam Eqs L Biotech C USD Cap
A19: 1 | B19: 1 | C19: Optimal Income A-H Grs Acc Hdg EUR | D19: 29 | E19: 41794 | F19: 0 | G19: 2347.326 | H19: 18.249685 | I19: =G19*H19 -> 42837.96 | K19: =Sheet2!E24 -> 18.25 | L19: =IF(ROUND(H19-K19,2)=0,"",H19-K19) | N19: =Sheet2!C24 -> M G Optimal Income Euro A-H Acc
A20: 1 | B20: 5 | C20: DWS Deutschland LC | D20: 31 | E20: 41976 | F20: 0 | G20: 264.1805 | H20: 168.57001 | I20: =G20*H20 -> 44532.91 | K20: =Sheet2!E29 -> 168.57 | L20: =IF(ROUND(H20-K20,2)=0,"",H20-K20) | N20: =Sheet2!C29 -> 0
A21: 1 | B21: 3 | C21: Asian Smaller Companies Fund | D21: 41 | E21: 42047 | F21: 0 | G21: 174.229 | H21: 39.429136 | I21: =G21*H21 -> 6869.699 | K21: =Sheet2!E35 -> 39.43 | L21: =IF(ROUND(H21-K21,2)=0,"",H21-K21) | N21: =Sheet2!C35 -> abrdnI-Asian Smaller Companies A Acc USD
A22: 1 | B22: 1 | C22: Optimal Income A-H Grs Acc Hdg EUR | D22: 92 | E22: 42202.719 | F22: 0 | G22: 2922.36 | H22: 18.3931 | I22: =G22*H22 -> 53751.26 | K22: =Sheet2!E36 -> 18.39 | L22: =IF(ROUND(H22-K22,2)=0,"",H22-K22) | N22: =Sheet2!C36 -> M G Optimal Income Euro A-H Acc
A23: 1 | B23: 6 | C23: Biotechnology C USD Acc | D23: 96 | E23: 42208.759 | F23: 0 | G23: 10.043 | H23: 591.12317 | I23: =G23*H23 -> 5936.65 | K23: =Sheet2!E43 -> 591.15 | L23: =IF(ROUND(H23-K23,2)=0,"",H23-K23) -> -0.026829633 | M23: =L23*G23 -> -0.26945 | N23: =Sheet2!C43 -> Candriam Eqs L Biotech C USD Cap
A24: 1 | B24: 15 | C24: Templeton Emerging Mkts Sm Cos N Acc $ | D24: 98 | E24: 42219.795 | F24: 0 | G24: 112.246 | H24: 8.9090034 | I24: =G24*H24 -> 1000 | K24: =Sheet2!E44 -> 8.91 | L24: =IF(ROUND(H24-K24,2)=0,"",H24-K24) | N24: =Sheet2!C44 -> Templeton Em Mkts Smlr Coms N(acc)USD
A25: 1 | B25: 16 | C25: DWS Aktien Strategie Deutschland | D25: 101 | E25: 42279.464 | F25: 0 | G25: 160.7528 | H25: 323.52998 | I25: =G25*H25 -> 52008.35 | K25: =Sheet2!E45 -> 323.53 | L25: =IF(ROUND(H25-K25,2)=0,"",H25-K25) | N25: =Sheet2!C45 -> 0
A26: 1 | B26: 6 | C26: Biotechnology C USD Acc | D26: 104 | E26: 42311.831 | F26: 0 | G26: 0.047 | H26: 507.02128 | I26: =G26*H26 -> 23.83 | K26: =Sheet2!E51 -> 507.43 | L26: =IF(ROUND(H26-K26,2)=0,"",H26-K26) -> -0.4087234 | M26: =L26*G26 -> -0.01921 | N26: =Sheet2!C51 -> Candriam Eqs L Biotech C USD Cap
A27: 1 | B27: 19 | C27: Trea Renta Fija Ahorro S FI | D27: 108 | E27: 42387.493 | F27: 0 | G27: 0.5375 | H27: 1860.4651 | I27: =G27*H27 -> 1000 | K27: =Sheet2!E52 -> 1860.41 | L27: =IF(ROUND(H27-K27,2)=0,"",H27-K27) -> 0.055116279 | M27: =L27*G27 -> 0.029625 | N27: =Sheet2!C52 -> Trea Renta Fija Ahorro S FI
A28: 1 | B28: 15 | C28: Templeton Emerging Mkts Sm Cos N Acc $ | D28: 122 | E28: 42635.715 | F28: 0 | G28: 5585.159 | H28: 8.952 | I28: =G28*H28 -> 49998.343 | K28: =Sheet2!E55 -> 8.95 | L28: =IF(ROUND(H28-K28,2)=0,"",H28-K28) | N28: =Sheet2!C55 -> Templeton Em Mkts Smlr Coms N(acc)USD
A29: 1 | B29: 19 | C29: Trea Renta Fija Ahorro S FI | D29: 171 | E29: 43516.388 | F29: 0 | G29: 0.4678 | H29: 1895.2417 | I29: =G29*H29 -> 886.59407 | K29: =Sheet2!E56 -> 1895.25 | L29: =IF(ROUND(H29-K29,2)=0,"",H29-K29) -> -0.0083 | M29: =L29*G29 -> -0.00388274 | N29: =Sheet2!C56 -> Trea Renta Fija Ahorro S FI
A30: 1 | B30: 27 | C30: Global Technology Fund A-acc-eur | D30: 173 | E30: 43525.444 | F30: 0 | G30: 1778.69 | H30: 17.05 | I30: =G30*H30 -> 30326.665 | K30: =Sheet2!E57 -> 17.05 | L30: =IF(ROUND(H30-K30,2)=0,"",H30-K30) | N30: =Sheet2!C57 -> Fidelity Global Technology A-ACC-EUR
A31: 1 | B31: 28 | C31: Euro Fund A-2 Acc | D31: 197 | E31: 44473.585 | F31: 0 | G31: 24.54 | H31: 435.10187 | I31: =G31*H31 -> 10677.4 | K31: =Sheet2!E58 -> 435.1 | L31: =IF(ROUND(H31-K31,2)=0,"",H31-K31) | N31: =Sheet2!C58 -> abrdn Euro Fund A-2
A32: 1 | B32: 29 | C32: CS Corto Plazo B FI | D32: 199 | E32: 44476.939 | F32: 0 | G32: 765.3691 | H32: 13.039504 | I32: =G32*H32 -> 9980.0331 | K32: =Sheet2!E59 -> 13.04 | L32: =IF(ROUND(H32-K32,2)=0,"",H32-K32) | N32: =Sheet2!C59 -> CS Corto Plazo B FI
A33: 1 | B33: 19 | C33: Trea Renta Fija Ahorro S FI | D33: 201 | E33: 44477.939 | F33: 0 | G33: 5.1658 | H33: 1904.1616 | I33: =G33*H33 -> 9836.5181 | K33: =Sheet2!E60 -> 1904.16 | L33: =IF(ROUND(H33-K33,2)=0,"",H33-K33) | N33: =Sheet2!C60 -> Trea Renta Fija Ahorro S FI
A34: 1 | B34: 28 | C34: Euro Fund A-2 Acc | D34: 203 | E34: 44496.481 | F34: 0 | G34: 34.724 | H34: 434.94679 | I34: =G34*H34 -> 15103.092 | K34: =Sheet2!E61 -> 434.94 | L34: =IF(ROUND(H34-K34,2)=0,"",H34-K34) -> 0.0067941481 | M34: =L34*G34 -> 0.23592 | N34: =Sheet2!C61 -> abrdn Euro Fund A-2
A35: 1 | B35: 28 | C35: Euro Fund A-2 Acc | D35: 205 | E35: 44524.517 | F35: 0 | G35: 46.266 | H35: 434.75771 | I35: =G35*H35 -> 20114.5 | K35: =Sheet2!E62 -> 434.76 | L35: =IF(ROUND(H35-K35,2)=0,"",H35-K35) | N35: =Sheet2!C62 -> abrdn Euro Fund A-2
A36: 1 | B36: 28 | C36: Euro Fund A-2 Acc | D36: 217 | E36: 44725.295 | F36: 0 | G36: 23.23 | H36: 433.28309 | I36: =G36*H36 -> 10065.166 | K36: =Sheet2!E63 -> 433.29 | L36: =IF(ROUND(H36-K36,2)=0,"",H36-K36) -> -0.0069091692 | M36: =L36*G36 -> -0.1605 | N36: =Sheet2!C63 -> abrdn Euro Fund A-2
A37: 1 | B37: 30 | C37: BGF World Energy E2 | D37: 219 | E37: 44736.475 | F37: 0 | G37: 565.1 | H37: 17.241866 | I37: =G37*H37 -> 9743.3787 | K37: =Sheet2!E64 -> 17.24 | L37: =IF(ROUND(H37-K37,2)=0,"",H37-K37) | N37: =Sheet2!C64 -> BGF World Energy E2
A38: 1 | B38: 1036 | C38: CS (Lux) Commodity Idx Plus USD B | D38: 1228 | E38: 44832.415 | F38: 0 | G38: 130.14 | H38: 76.532599 | I38: =G38*H38 -> 9959.9524 | K38: =Sheet2!E65 -> 76.53 | L38: =IF(ROUND(H38-K38,2)=0,"",H38-K38) | N38: =Sheet2!C65 -> CS (Lux) Commodity Idx Plus USD B
A39: 1 | B39: 1037 | C39: Threadneedle (Lux) Enhanced | D39: 1231 | E39: 44861.454 | F39: 0 | G39: 810.714 | H39: 10.282473 | I39: =G39*H39 -> 8336.1445 | K39: =Sheet2!E66 -> 10.28 | L39: =IF(ROUND(H39-K39,2)=0,"",H39-K39) | N39: =Sheet2!C66 -> Threadneedle (Lux) Enhanced Cmdts DU
A40: 1 | B40: 1038 | C40: Abrdn US Dollar Fund A-2 | D40: 1233 | E40: 44879.428 | F40: 0 | G40: 0.83 | H40: 3310.2667 | I40: =G40*H40 -> 2747.5214 | K40: =Sheet2!E67 -> 3308.42 | L40: =IF(ROUND(H40-K40,2)=0,"",H40-K40) -> 1.8466874 | M40: =L40*G40 -> 1.5327505 | N40: =Sheet2!C67 -> abrdn US Dollar Fund A-2
A41: 1 | B41: 28 | C41: Euro Fund A-2 Acc | D41: 1235 | E41: 44893.559 | F41: 0 | G41: 21.81 | H41: 433.51992 | I41: =G41*H41 -> 9455.0694 | K41: =Sheet2!E68 -> 433.52 | L41: =IF(ROUND(H41-K41,2)=0,"",H41-K41) | N41: =Sheet2!C68 -> abrdn Euro Fund A-2
A42: 1 | B42: 28 | C42: Euro Fund A-2 Acc | D42: 1239 | E42: 44893.573 | F42: 0 | G42: 18.636 | H42: 433.54193 | I42: =G42*H42 -> 8079.4874 | K42: =Sheet2!E69 -> 433.52 | L42: =IF(ROUND(H42-K42,2)=0,"",H42-K42) -> 0.021927247 | M42: =L42*G42 -> 0.40863617 | N42: =Sheet2!C69 -> abrdn Euro Fund A-2
A43: 1 | B43: 28 | C43: Euro Fund A-2 Acc | D43: 1241 | E43: 44939.567 | F43: 0 | G43: 5.872 | H43: 434.45089 | I43: =G43*H43 -> 2551.0956 | K43: =Sheet2!E70 -> 434.43 | L43: =IF(ROUND(H43-K43,2)=0,"",H43-K43) -> 0.020888862 | M43: =L43*G43 -> 0.1226594 | N43: =Sheet2!C70 -> abrdn Euro Fund A-2
A44: 1 | B44: 1039 | C44: Carmignac Court Terme A Eur Acc | D44: 1246 | E44: 45028.467 | F44: 0 | G44: 0.332 | H44: 3710.1159 | I44: =G44*H44 -> 1231.7585 | K44: =Sheet2!E71 -> 3700.36 | L44: =IF(ROUND(H44-K44,2)=0,"",H44-K44) -> 9.7558795 | M44: =L44*G44 -> 3.238952 | N44: =Sheet2!C71 -> Carmignac Court Terme A EUR Acc
A45: 1 | B45: 1040 | C45: World Gold Fund E2 | D45: 1248 | E45: 45029.467 | F45: 0 | G45: 187.71 | H45: 31.669576 | I45: =G45*H45 -> 5944.6962 | K45: =Sheet2!E72 -> 31.67 | L45: =IF(ROUND(H45-K45,2)=0,"",H45-K45) | N45: =Sheet2!C72 -> BGF World Gold E2
A46: 1 | B46: 1039 | C46: Carmignac Court Terme A Eur Acc | D46: 1250 | E46: 45043.365 | F46: 0 | G46: 2.804 | H46: 3705.3528 | I46: =G46*H46 -> 10389.809 | K46: =Sheet2!E73 -> 3705.25 | L46: =IF(ROUND(H46-K46,2)=0,"",H46-K46) -> 0.10284019 | M46: =L46*G46 -> 0.2883639 | N46: =Sheet2!C73 -> Carmignac Court Terme A EUR Acc
A47: 1 | B47: 1041 | C47: Pictet-short-term Money Market Chf R | D47: 1253 | E47: 45061.371 | F47: 0 | G47: 8.40958 | H47: 118.91483 | I47: =G47*H47 -> 1000.0238 | K47: =Sheet2!E74 -> 118.91 | L47: =IF(ROUND(H47-K47,2)=0,"",H47-K47) | N47: =Sheet2!C74 -> Pictet-Short-Term Money Market CHF R
A48: 1 | B48: 1041 | C48: Pictet-short-term Money Market Chf R | D48: 1254 | E48: 45069.726 | F48: 0 | G48: 74.80175 | H48: 120.31804 | I48: =G48*H48 -> 9000 | K48: =Sheet2!E75 -> 120.32 | L48: =IF(ROUND(H48-K48,2)=0,"",H48-K48) | N48: =Sheet2!C75 -> Pictet-Short-Term Money Market CHF R
A52: 1 | B52: 10 | C52: Bolsa Tecnología y Telecomunicaciones FI | D52: 23 | E52: 41383 | F52: 1 | G52: 679.64 | H52: 8.1098376 | I52: =G52*H52 -> 5511.77
A53: 1 | B53: 12 | C53: American Extended Alpha R USD Acc | D53: 33 | E53: 41385 | F53: 1 | G53: 5006.5079 | H53: 2.0725624 | I53: =G53*H53 -> 10376.3 | K53: =Sheet2!E77 -> 2.07 | L53: =IF(ROUND(H53-K53,2)=0,"",H53-K53)
A54: 1 | B54: 14 | C54: Patrimoine A EUR Acc | D54: 36 | E54: 41436 | F54: 1 | G54: 21.84 | H54: 547.44002 | I54: =G54*H54 -> 11956.09 | L54: =IF(ROUND(H54-K54,2)=0,"",H54-K54) -> 547.44002
A55: 1 | B55: 13 | C55: Indonesia Fund A-USD | D55: 42 | E55: 41436 | F55: 1 | G55: 394.85 | H55: 24.609001 | I55: =G55*H55 -> 9716.864 | K55: =Sheet2!E78 -> 24.61 | L55: =IF(ROUND(H55-K55,2)=0,"",H55-K55)
A56: 1 | B56: 3 | C56: Asian Smaller Companies Fund | D56: 4 | E56: 41438 | F56: 1 | G56: 1415.582 | H56: 33.983393 | I56: =G56*H56 -> 48106.28 | K56: =Sheet2!E79 -> 34.68 | L56: =IF(ROUND(H56-K56,2)=0,"",H56-K56) -> -0.6966066
A57: 1 | B57: 11 | C57: Total Return N Acc €-H1 | D57: 25 | E57: 41439 | F57: 1 | G57: 1838.3261 | H57: 18.95 | I57: =G57*H57 -> 34836.28 | K57: =Sheet2!E80 -> 18.95 | L57: =IF(ROUND(H57-K57,2)=0,"",H57-K57)
A58: 1 | B58: 3 | C58: Asian Smaller Companies Fund | D58: 5 | E58: 41492 | F58: 1 | G58: 178 | H58: 33.896399 | I58: =G58*H58 -> 6033.559 | K58: =Sheet2!E81 -> 33.9 | L58: =IF(ROUND(H58-K58,2)=0,"",H58-K58)
A59: 1 | B59: 3 | C59: Asian Smaller Companies Fund | D59: 6 | E59: 41506 | F59: 1 | G59: 522.002 | H59: 32.470297 | I59: =G59*H59 -> 16949.56 | K59: =Sheet2!E82 -> 32.47 | L59: =IF(ROUND(H59-K59,2)=0,"",H59-K59)
A60: 1 | B60: 4 | C60: Thailand A-USD | D60: 13 | E60: 41639 | F60: 1 | G60: 160 | H60: 30.94775 | I60: =G60*H60 -> 4951.64 | K60: =Sheet2!E83 -> 30.95 | L60: =IF(ROUND(H60-K60,2)=0,"",H60-K60)
A61: 1 | B61: 2 | C61: European Growth N Acc ? | D61: 38 | E61: 41673 | F61: 1 | G61: 75 | H61: 12.78 | I61: =G61*H61 -> 958.5 | K61: =Sheet2!E84 -> 12.78 | L61: =IF(ROUND(H61-K61,2)=0,"",H61-K61)
A62: 1 | B62: 5 | C62: DWS Deutschland LC | D62: 28 | E62: 41794 | F62: 1 | G62: 249 | H62: 172.04 | I62: =G62*H62 -> 42837.96 | K62: =Sheet2!E85 -> 172.04 | L62: =IF(ROUND(H62-K62,2)=0,"",H62-K62)
A63: 1 | B63: 1 | C63: Optimal Income A-H Grs Acc Hdg EUR | D63: 30 | E63: 41971 | F63: 1 | G63: 2404 | H63: 18.524505 | I63: =G63*H63 -> 44532.91 | K63: =Sheet2!E86 -> 18.52 | L63: =IF(ROUND(H63-K63,2)=0,"",H63-K63)
A64: 1 | B64: 6 | C64: Biotechnology C USD Acc | D64: 40 | E64: 42047 | F64: 1 | G64: 15 | H64: 457.97993 | I64: =G64*H64 -> 6869.699 | K64: =Sheet2!E87 -> 457.98 | L64: =IF(ROUND(H64-K64,2)=0,"",H64-K64)
A65: 1 | B65: 5 | C65: DWS Deutschland LC | D65: 91 | E65: 42201.719 | F65: 1 | G65: 259.53 | H65: 207.11001 | I65: =G65*H65 -> 53751.26 | K65: =Sheet2!E88 -> 207.11 | L65: =IF(ROUND(H65-K65,2)=0,"",H65-K65)
A66: 1 | B66: 3 | C66: Asian Smaller Companies Fund | D66: 95 | E66: 42207.759 | F66: 1 | G66: 150 | H66: 39.577667 | I66: =G66*H66 -> 5936.65 | K66: =Sheet2!E89 -> 39.58 | L66: =IF(ROUND(H66-K66,2)=0,"",H66-K66)
... A70: 1 | B70: 16 | C70: DWS Aktien Strategie Deutschland | D70: 172 | E70: 43525.444 | F70: 1 | G70: 80.7528 | H70: 375.55 | I70: =G70*H70 -> 30326.714 | K70: =Sheet2!E93 -> 375.55 | L70: =IF(ROUND(H70-K70,2)=0,"",H70-K70)
A71: 1 | B71: 4 | C71: Thailand A-USD | D71: 186 | E71: 44176.608 | F71: 1 | G71: 3.14 | H71: 42.410766 | I71: =G71*H71 -> 133.16981 | K71: =Sheet2!E95 -> 42.41 | L71: =IF(ROUND(H71-K71,2)=0,"",H71-K71)
A72: 1 | B72: 3 | C72: Asian Smaller Companies Fund | D72: 187 | E72: 44176.609 | F72: 1 | G72: 24.229 | H72: 42.515788 | I72: =G72*H72 -> 1030.115 | K72: =Sheet2!E96 -> 42.52 | L72: =IF(ROUND(H72-K72,2)=0,"",H72-K72)
A73: 1 | B73: 15 | C73: Templeton Emerging Mkts Sm Cos N Acc $ | D73: 188 | E73: 44179.383 | F73: 1 | G73: 5697.405 | H73: 9.320687 | I73: =G73*H73 -> 53103.729
A74: 1 | B74: 16 | C74: DWS Aktien Strategie Deutschland | D74: 196 | E74: 44469.586 | F74: 1 | G74: 20 | H74: 533.87 | I74: =G74*H74 -> 10677.4 | K74: =Sheet2!E97 -> 533.87 | L74: =IF(ROUND(H74-K74,2)=0,"",H74-K74)
A75: 1 | B75: 27 | C75: Global Technology Fund A-acc-eur | D75: 198 | E75: 44470.941 | F75: 1 | G75: 287.03 | H75: 34.77 | I75: =G75*H75 -> 9980.0331 | K75: =Sheet2!E98 -> 34.77 | L75: =IF(ROUND(H75-K75,2)=0,"",H75-K75)
A76: 1 | B76: 27 | C76: Global Technology Fund A-acc-eur | D76: 200 | E76: 44473.943 | F76: 1 | G76: 287.03 | H76: 34.27 | I76: =G76*H76 -> 9836.5181 | K76: =Sheet2!E99 -> 34.27 | L76: =IF(ROUND(H76-K76,2)=0,"",H76-K76)
A77: 1 | B77: 6 | C77: Biotechnology C USD Acc | D77: 202 | E77: 44491.487 | F77: 1 | G77: 22.326 | H77: 676.48 | I77: =G77*H77 -> 15103.092 | K77: =Sheet2!E100 -> 676.48 | L77: =IF(ROUND(H77-K77,2)=0,"",H77-K77)
A78: 1 | B78: 16 | C78: DWS Aktien Strategie Deutschland | D78: 204 | E78: 44522.519 | F78: 1 | G78: 35 | H78: 574.7 | I78: =G78*H78 -> 20114.5 | K78: =Sheet2!E101 -> 574.7 | L78: =IF(ROUND(H78-K78,2)=0,"",H78-K78)
A79: 1 | B79: 27 | C79: Global Technology Fund A-acc-eur | D79: 216 | E79: 44720.299 | F79: 1 | G79: 296.82 | H79: 33.91 | I79: =G79*H79 -> 10065.166 | K79: =Sheet2!E102 -> 33.91 | L79: =IF(ROUND(H79-K79,2)=0,"",H79-K79)
A80: 1 | B80: 16 | C80: DWS Aktien Strategie Deutschland | D80: 218 | E80: 44734.477 | F80: 1 | G80: 23.3699 | H80: 416.92 | I80: =G80*H80 -> 9743.3787 | K80: =Sheet2!E103 -> 416.92 | L80: =IF(ROUND(H80-K80,2)=0,"",H80-K80)
A81: 1 | B81: 27 | C81: Global Technology Fund A-acc-eur | D81: 1227 | E81: 44831.416 | F81: 1 | G81: 308.74 | H81: 32.26 | I81: =G81*H81 -> 9959.9524 | K81: =Sheet2!E104 -> 32.26 | L81: =IF(ROUND(H81-K81,2)=0,"",H81-K81)
A82: 1 | B82: 29 | C82: CS Corto Plazo B FI | D82: 1229 | E82: 44844.784 | F82: 1 | G82: 765.3691 | H82: 12.534 | I82: =G82*H82 -> 9593.1363 | K82: =Sheet2!E105 -> 12.53 | L82: =IF(ROUND(H82-K82,2)=0,"",H82-K82)
A83: 1 | B83: 19 | C83: Trea Renta Fija Ahorro S FI | D83: 1230 | E83: 44855.456 | F83: 1 | G83: 4.642 | H83: 1795.8088 | I83: =G83*H83 -> 8336.1445 | K83: =Sheet2!E106 -> 1795.81 | L83: =IF(ROUND(H83-K83,2)=0,"",H83-K83)
A84: 1 | B84: 19 | C84: Trea Renta Fija Ahorro S FI | D84: 1232 | E84: 44874.431 | F84: 1 | G84: 1.5291 | H84: 1796.8225 | I84: =G84*H84 -> 2747.5214 | K84: =Sheet2!E107 -> 1796.82 | L84: =IF(ROUND(H84-K84,2)=0,"",H84-K84)
A85: 1 | B85: 1037 | C85: Threadneedle (Lux) Enhanced | D85: 1238 | E85: 44890.573 | F85: 1 | G85: 810.714 | H85: 9.965891 | I85: =G85*H85 -> 8079.4874 | K85: =Sheet2!E108 -> 9.97 | L85: =IF(ROUND(H85-K85,2)=0,"",H85-K85)
... A92: 1 | B92: 27 | C92: Global Technology Fund A-acc-eur | D92: 1251 | E92: 45054.531 | F92: 1 | G92: 270 | H92: 34.29 | I92: =G92*H92 -> 9258.3 | K92: =Sheet2!E115 -> 34.29 | L92: =IF(ROUND(H92-K92,2)=0,"",H92-K92)

Sheet Sheet2
A1: Fecha | B1: Movimiento | C1: Valor | D1: Cantidad | E1: Precio Ejecución | F1: Importe Bruto | G1: Importe total | H1: Plusvalía/Minusvalía
A2: 41169 | B2: Suscripción fondo | C2: Templeton Global Ttl Ret N(acc)EUR-H1 | D2: 547.65 | E2: 18.26 | F2: -10000 | G2: -10000
A3: 41169 | B3: Suscripción fondo | C3: Threadneedle Amer Extnd Alpha Rtl AccUSD | D3: 5006.51 | E3: 2 | F3: -10000 | G3: -10000
A4: 41172 | B4: Suscripción fondo | C4: abrdnI-Asian Smaller Companies A Acc USD | D4: 325.52 | E4: 30.72 | F4: -10000.01 | G4: -10000.01
A5: 41187 | B5: Suscripción fondo | C5: abrdnI-Asian Smaller Companies A Acc USD | D5: 1267.69 | E5: 31.55 | F5: -39999.98 | G5: -39999.98
A6: 41375 | B6: Suscripción fondo | C6: Templeton Global Ttl Ret N(acc)EUR-H1 | D6: 1010.61 | E6: 19.79 | F6: -19999.99 | G6: -19999.99
A7: 41381 | B7: Suscripción traspaso de fondo | C7: Templeton Global Ttl Ret N(acc)EUR-H1 | D7: 12.65 | E7: 19.68 | F7: -248.93 | G7: 0
A8: 41381 | B8: Suscripción traspaso de fondo | C8: Templeton Global Ttl Ret N(acc)EUR-H1 | D8: 68.92 | E8: 19.68 | F8: -1356.24 | G8: 0
A9: 41381 | B9: Suscripción traspaso de fondo | C9: Templeton Global Ttl Ret N(acc)EUR-H1 | D9: 198.51 | E9: 19.68 | F9: -3906.6 | G9: 0
A10: 41387 | B10: Suscripción traspaso de fondo | C10: Fidelity Indonesia A-Dis-USD | D10: 394.85 | E10: 26.28 | F10: -10376.3 | G10: 0
A11: 41409 | B11: Suscripción fondo | C11: abrdnI-Asian Smaller Companies A Acc USD | D11: 522.37 | E11: 38.29 | F11: -20000.02 | G11: -20000.02
A12: 41437 | B12: Suscripción traspaso de fondo | D12: 1.72 | E12: 139.71 | F12: -239.7 | G12: 0
A13: 41437 | B13: Suscripción traspaso de fondo | D13: 9.35 | E13: 139.71 | F13: -1305.94 | G13: 0
A14: 41437 | B14: Suscripción traspaso de fondo | D14: 26.93 | E14: 139.71 | F14: -3761.69 | G14: 0
A15: 41437 | B15: Suscripción traspaso de fondo | D15: 74.28 | E15: 139.71 | F15: -10377.87 | G15: 0
A16: 41437 | B16: Suscripción traspaso de fondo | D16: 137.08 | E16: 139.71 | F16: -19151.08 | G16: 0
A17: 41492 | B17: Suscripción traspaso de fondo | C17: Candriam Eqs L Biotech C USD Cap | D17: 24.04 | E17: 250.44 | F17: -6020.89 | G17: 0
A18: 41492 | B18: Suscripción traspaso de fondo | C18: Candriam Eqs L Biotech C USD Cap | D18: 0.05 | E18: 250.44 | F18: -12.67 | G18: 0
A19: 41519 | B19: Suscripción fondo | C19: M G Optimal Income Euro A-H Acc | D19: 58.5 | E19: 17.09 | F19: -999.99 | G19: -999.99
A20: 41530 | B20: Suscripción fondo | C20: Templeton European Opps N(acc)EUR | D20: 76.75 | E20: 13.03 | F20: -1000 | G20: -1000
A21: 41554 | B21: Suscripción fondo | C21: Fidelity Thailand A-Dis-USD | D21: 28.28 | E21: 35.36 | F21: -999.9 | G21: -999.9
A22: 41563 | B22: Suscripción fondo | C22: Fidelity Thailand A-Dis-USD | D22: 134.86 | E22: 37.08 | F22: -5000.11 | G22: -5000.11
A23: 41669 | B23: Suscripción traspaso de fondo | C23: Candriam Eqs L Biotech C USD Cap | D23: 3.14 | E23: 304.86 | F23: -958.5 | G23: 0
A24: 41793 | B24: Suscripción traspaso de fondo | C24: M G Optimal Income Euro A-H Acc | D24: 16.17 | E24: 18.25 | F24: -295.17 | G24: 0
A25: 41793 | B25: Suscripción traspaso de fondo | C25: M G Optimal Income Euro A-H Acc | D25: 88.12 | E25: 18.25 | F25: -1608.14 | G25: 0
A26: 41793 | B26: Suscripción traspaso de fondo | C26: M G Optimal Income Euro A-H Acc | D26: 253.82 | E26: 18.25 | F26: -4632.18 | G26: 0
A27: 41793 | B27: Suscripción traspaso de fondo | C27: M G Optimal Income Euro A-H Acc | D27: 700.25 | E27: 18.25 | F27: -12779.39 | G27: 0
A28: 41793 | B28: Suscripción traspaso de fondo | C28: M G Optimal Income Euro A-H Acc | D28: 1288.96 | E28: 18.25 | F28: -23523.08 | G28: 0
A29: 41976 | B29: Suscripción traspaso de fondo | D29: 1.78 | E29: 168.57 | F29: -299.62 | G29: 0
A30: 41976 | B30: Suscripción traspaso de fondo | D30: 9.68 | E30: 168.57 | F30: -1632.36 | G30: 0
A31: 41976 | B31: Suscripción traspaso de fondo | D31: 27.89 | E31: 168.57 | F31: -4701.93 | G31: 0
A32: 41976 | B32: Suscripción traspaso de fondo | D32: 76.95 | E32: 168.57 | F32: -12971.84 | G32: 0
A33: 41976 | B33: Suscripción traspaso de fondo | D33: 141.65 | E33: 168.57 | F33: -23877.3 | G33: 0
A34: 41976 | B34: Suscripción traspaso de fondo | D34: 6.23 | E34: 168.57 | F34: -1049.86 | G34: 0
A35: 42046 | B35: Suscripción traspaso de fondo | C35: abrdnI-Asian Smaller Companies A Acc USD | D35: 174.23 | E35: 39.43 | F35: -6869.7 | G35: 0
A36: 42202 | B36: Suscripción traspaso de fondo | C36: M G Optimal Income Euro A-H Acc | D36: 20.01 | E36: 18.39 | F36: -368.12 | G36: 0
A37: 42202 | B37: Suscripción traspaso de fondo | C37: M G Optimal Income Euro A-H Acc | D37: 109.04 | E37: 18.39 | F37: -2005.57 | G37: 0
A38: 42202 | B38: Suscripción traspaso de fondo | C38: M G Optimal Income Euro A-H Acc | D38: 314.08 | E38: 18.39 | F38: -5776.92 | G38: 0
A39: 42202 | B39: Suscripción traspaso de fondo | C39: M G Optimal Income Euro A-H Acc | D39: 866.5 | E39: 18.39 | F39: -15937.59 | G39: 0
A40: 42202 | B40: Suscripción traspaso de fondo | C40: M G Optimal Income Euro A-H Acc | D40: 1594.96 | E40: 18.39 | F40: -29336.35 | G40: 0
A41: 42202 | B41: Suscripción traspaso de fondo | C41: M G Optimal Income Euro A-H Acc | D41: 13.86 | E41: 18.39 | F41: -254.83 | G41: 0
A42: 42202 | B42: Suscripción traspaso de fondo | C42: M G Optimal Income Euro A-H Acc | D42: 3.91 | E42: 18.39 | F42: -71.89 | G42: 0
A43: 42208 | B43: Suscripción traspaso de fondo | C43: Candriam Eqs L Biotech C USD Cap | D43: 10.04 | E43: 591.15 | F43: -5936.64 | G43: 0
A44: 42219 | B44: Suscripción fondo | C44: Templeton Em Mkts Smlr Coms N(acc)USD | D44: 112.25 | E44: 8.91 | F44: -1000 | G44: -1000
A45: 42284 | B45: Suscripción traspaso de fondo | D45: 1.12 | E45: 323.53 | F45: -361.52 | G45: 0
A46: 42284 | B46: Suscripción traspaso de fondo | D46: 6.09 | E46: 323.53 | F46: -1969.59 | G46: 0
A47: 42284 | B47: Suscripción traspaso de fondo | D47: 17.54 | E47: 323.53 | F47: -5673.31 | G47: 0
A48: 42284 | B48: Suscripción traspaso de fondo | D48: 48.38 | E48: 323.53 | F48: -15651.73 | G48: 0
A49: 42284 | B49: Suscripción traspaso de fondo | D49: 87.42 | E49: 323.53 | F49: -28281.59 | G49: 0
A50: 42284 | B50: Suscripción traspaso de fondo | D50: 0.22 | E50: 323.53 | F50: -70.61 | G50: 0
A51: 42311 | B51: Suscripción traspaso de fondo | C51: Candriam Eqs L Biotech C USD Cap | D51: 0.05 | E51: 507.43 | F51: -23.83 | G51: 0
A52: 42387 | B52: Suscripción fondo | C52: Trea Renta Fija Ahorro S FI | D52: 0.54 | E52: 1860.41 | F52: -1000 | G52: -1000
A53: 42387 | B53: Suscripción fondo | C53: Trea Renta Fija Ahorro S FI | D53: 0.54 | E53: 1860.41 | F53: -1000 | G53: -1000
A54: 42387 | B54: Suscripción fondo | C54: Trea Renta Fija Ahorro S FI | D54: 0.54 | E54: 0 | F54: -1000 | G54: -1000
A55: 42635 | B55: Suscripción fondo | C55: Templeton Em Mkts Smlr Coms N(acc)USD | D55: 5585.16 | E55: 8.95 | F55: -50000 | G55: -50000
A56: 43516 | B56: Suscripción traspaso de fondo | C56: Trea Renta Fija Ahorro S FI | D56: 0.47 | E56: 1895.25 | F56: -886.59 | G56: 0
A57: 43525 | B57: Suscripción traspaso de fondo | C57: Fidelity Global Technology A-ACC-EUR | D57: 1778.69 | E57: 17.05 | F57: -30326.71 | G57: 0
A58: 44473 | B58: Suscripción traspaso de fondo | C58: abrdn Euro Fund A-2 | D58: 24.54 | E58: 435.1 | F58: -10677.4 | G58: 0
A59: 44476 | B59: Suscripción traspaso de fondo | C59: CS Corto Plazo B FI | D59: 765.37 | E59: 13.04 | F59: -9980.03 | G59: 0
A60: 44477 | B60: Suscripción traspaso de fondo | C60: Trea Renta Fija Ahorro S FI | D60: 5.17 | E60: 1904.16 | F60: -9836.52 | G60: 0
A61: 44496 | B61: Suscripción traspaso de fondo | C61: abrdn Euro Fund A-2 | D61: 34.72 | E61: 434.94 | F61: -15102.95 | G61: 0
A62: 44524 | B62: Suscripción traspaso de fondo | C62: abrdn Euro Fund A-2 | D62: 46.27 | E62: 434.76 | F62: -20114.51 | G62: 0
... A75: 45069 | B75: Suscripción fondo | C75: Pictet-Short-Term Money Market CHF R | D75: 74.8 | E75: 120.32 | F75: -9000 | G75: -9000
A77: 41386 | B77: Reembolso traspaso fondo | C77: Threadneedle Amer Extnd Alpha Rtl AccUSD | D77: 5006.51 | E77: 2.07 | F77: 10376.3 | G77: 0 | H77: 376.3
A78: 41432 | B78: Reembolso fondo | C78: Fidelity Indonesia A-Dis-USD | D78: 394.85 | E78: 24.61 | F78: 9716.73 | G78: 9716.73 | H78: -659.57
A79: 41436 | B79: Reembolso fondo | C79: abrdnI-Asian Smaller Companies A Acc USD | D79: 1415.58 | E79: 34.68 | F79: 49092.77 | G79: 48106.28 | H79: 2254.25
A80: 41436 | B80: Reembolso traspaso fondo | C80: Templeton Global Ttl Ret N(acc)EUR-H1 | D80: 1838.33 | E80: 18.95 | F80: 34836.28 | G80: 0 | H80: -675.48
A81: 41491 | B81: Reembolso traspaso fondo | C81: abrdnI-Asian Smaller Companies A Acc USD | D81: 178 | E81: 33.9 | F81: 6033.57 | G81: 0 | H81: 143.92
A82: 41506 | B82: Reembolso fondo | C82: abrdnI-Asian Smaller Companies A Acc USD | D82: 522 | E82: 32.47 | F82: 16949.56 | G82: 16949.56 | H82: -322.27
A83: 41638 | B83: Reembolso fondo | C83: Fidelity Thailand A-Dis-USD | D83: 160 | E83: 30.95 | F83: 4951.64 | G83: 4951.64 | H83: -932.89
A84: 41668 | B84: Reembolso traspaso fondo | C84: Templeton European Opps N(acc)EUR | D84: 75 | E84: 12.78 | F84: 958.5 | G84: 0 | H84: -18.75
A85: 41792 | B85: Reembolso traspaso fondo | D85: 249 | E85: 172.04 | F85: 42837.96 | G85: 0 | H85: 8050.17
A86: 41971 | B86: Reembolso traspaso fondo | C86: M G Optimal Income Euro A-H Acc | D86: 2404 | E86: 18.52 | F86: 44532.9 | G86: 0 | H86: 728.26
A87: 42044 | B87: Reembolso traspaso fondo | C87: Candriam Eqs L Biotech C USD Cap | D87: 15 | E87: 457.98 | F87: 6869.7 | G87: 0 | H87: 3018.87
A88: 42201 | B88: Reembolso traspaso fondo | D88: 259.53 | E88: 207.11 | F88: 53751.26 | G88: 0 | H88: 10012.11
A89: 42207 | B89: Reembolso traspaso fondo | C89: abrdnI-Asian Smaller Companies A Acc USD | D89: 150 | E89: 39.58 | F89: 5936.65 | G89: 0 | H89: 22.29
A90: 42279 | B90: Reembolso traspaso fondo | C90: M G Optimal Income Euro A-H Acc | D90: 2879.24 | E90: 18.06 | F90: 52008.34 | G90: 0 | H90: -949.57
A91: 42310 | B91: Reembolso traspaso fondo | C91: Templeton European Opps N(acc)EUR | D91: 1.75 | E91: 13.65 | F91: 23.83 | G91: 0 | H91: 1.07
A92: 43510 | B92: Reembolso traspaso fondo | C92: M G Optimal Income Euro A-H Acc | D92: 44.95 | E92: 19.73 | F92: 886.59 | G92: 0
A93: 43524 | B93: Reembolso traspaso fondo | C93: DWS Aktien Strategie Deutschland LC | D93: 80.75 | E93: 375.55 | F93: 30326.71 | G93: 0
A94: 44176 | B94: Reembolso fondo | C94: Templeton Em Mkts Smlr Coms N(acc)USD | D94: 5697.41 | E94: 9.32 | F94: 53103.73 | G94: 52704.02 | H94: 2103.74
A95: 44176 | B95: Reembolso fondo | C95: Fidelity Thailand A-Dis-USD | D95: 3.14 | E95: 42.41 | F95: 133.17 | G95: 129.99 | H95: 16.75
A96: 44176 | B96: Reembolso fondo | C96: abrdnI-Asian Smaller Companies A Acc USD | D96: 24.23 | E96: 42.52 | F96: 1030.12 | G96: 926.79 | H96: 543.82
A97: 44469 | B97: Reembolso traspaso fondo | C97: DWS Aktien Strategie Deutschland LC | D97: 20 | E97: 533.87 | F97: 10677.4 | G97: 0
A98: 44470 | B98: Reembolso traspaso fondo | C98: Fidelity Global Technology A-ACC-EUR | D98: 287.03 | E98: 34.77 | F98: 9980.03 | G98: 0
A99: 44473 | B99: Reembolso traspaso fondo | C99: Fidelity Global Technology A-ACC-EUR | D99: 287.03 | E99: 34.27 | F99: 9836.52 | G99: 0
A100: 44491 | B100: Reembolso traspaso fondo | C100: Candriam Eqs L Biotech C USD Cap | D100: 22.33 | E100: 676.48 | F100: 15103.09 | G100: 0
A101: 44522 | B101: Reembolso traspaso fondo | C101: DWS Aktien Strategie Deutschland LC | D101: 35 | E101: 574.7 | F101: 20114.5 | G101: 0
A102: 44720 | B102: Reembolso traspaso fondo | C102: Fidelity Global Technology A-ACC-EUR | D102: 296.82 | E102: 33.91 | F102: 10065.17 | G102: 0
A103: 44734 | B103: Reembolso traspaso fondo | C103: DWS Aktien Strategie Deutschland LC | D103: 23.37 | E103: 416.92 | F103: 9743.38 | G103: 0
A104: 44831 | B104: Reembolso traspaso fondo | C104: Fidelity Global Technology A-ACC-EUR | D104: 308.74 | E104: 32.26 | F104: 9959.95 | G104: 0
A105: 44841 | B105: Reembolso fondo | C105: CS Corto Plazo B FI | D105: 765.37 | E105: 12.53 | F105: 9593.14 | G105: 9467.66 | H105: 660.43
A106: 44852 | B106: Reembolso traspaso fondo | C106: Trea Renta Fija Ahorro S FI | D106: 4.64 | E106: 1795.81 | F106: 8336.14 | G106: 0
A107: 44869 | B107: Reembolso traspaso fondo | C107: Trea Renta Fija Ahorro S FI | D107: 1.53 | E107: 1796.82 | F107: 2747.55 | G107: 0
A108: 44886 | B108: Reembolso traspaso fondo | C108: Threadneedle (Lux) Enhanced Cmdts DU | D108: 810.71 | E108: 9.97 | F108: 8079.49 | G108: 0
A109: 44886 | B109: Reembolso traspaso fondo | C109: CS (Lux) Commodity Idx Plus USD B | D109: 130.14 | E109: 72.65 | F109: 9455.07 | G109: 0
A110: 44937 | B110: Reembolso traspaso fondo | C110: abrdn US Dollar Fund A-2 | D110: 0.83 | E110: 3073.61 | F110: 2551.09 | G110: 0
A111: 45027 | B111: Reembolso traspaso fondo | C111: DWS Deutschland LC | D111: 5 | E111: 246.47 | F111: 1231.75 | G111: 0
A112: 45028 | B112: Reembolso traspaso fondo | C112: Fidelity Global Technology A-ACC-EUR | D112: 172.46 | E112: 34.47 | F112: 5944.7 | G112: 0
A113: 45043 | B113: Reembolso traspaso fondo | C113: BGF World Energy E2 | D113: 565.1 | E113: 18.39 | F113: 10389.81 | G113: 0
...
