Workbook

Sheet Compra 15
A1: Mov | B1: Id Mov | C1: Id Orig | D1: Nom Fons Orig | E1: Data Compra Venda | F1: Data Orig Compra | G1: PU | H1: PU Orig | I1: Parts Desg | J1: Parts Desg Orig | K1: Parts Util | L1: Parts Orig Ut | M1: Parts en cartera | N1: Parts orig en cartera | O1: Import Orig venda real | P1: Import Orig en cartera | Q1: Pig Origen venda real | R1: PiG Orig en cartera
A2: C | B2: 15 | C2: 15 | D2: Bolsa Tecnología y Telecomunicaciones FI | E2: 36841 | F2: 36841 | G2: 22.99204 | H2: 22.99204 | I2: 679.64 | J2: 679.64
A3: CT | B3: 24 | C3: 15 | D3: Bolsa Tecnología y Telecomunicaciones FI | E3: 41383 | F3: 36841 | G3: 19.679973 | H3: 22.99204 | I3: 280.07 | J3: 679.64
A4: CT | B4: 26 | C4: 15 | D4: Bolsa Tecnología y Telecomunicaciones FI | E4: 41439 | F4: 36841 | G4: 139.70999 | H4: 22.99204 | I4: 37.9882 | J4: 679.6401
A5: CT | B5: 29 | C5: 15 | D5: Bolsa Tecnología y Telecomunicaciones FI | E5: 41794 | F5: 36841 | G5: 18.249685 | H5: 22.99204 | I5: 358.1152 | J5: 679.6401
A6: CT | B6: 31 | C6: 15 | D6: Bolsa Tecnología y Telecomunicaciones FI | E6: 41976 | F6: 36841 | G6: 168.57001 | H6: 22.99204 | I6: 39.354 | J6: 679.6401
A7: CT | B7: 92 | C7: 15 | D7: Bolsa Tecnología y Telecomunicaciones FI | E7: 42202.719 | F7: 36841 | G7: 18.3931 | H7: 22.99204 | I7: 443.134 | J7: 679.6401
A8: CT | B8: 101 | C8: 15 | D8: Bolsa Tecnología y Telecomunicaciones FI | E8: 42279.464 | F8: 36841 | G8: 323.52998 | H8: 22.99204 | I8: 24.7409 | J8: 679.6401
A9: CT | B9: 173 | C9: 15 | D9: Bolsa Tecnología y Telecomunicaciones FI | E9: 43525.444 | F9: 36841 | G9: 17.05 | H9: 22.99204 | I9: 544.9519 | J9: 679.6401
A10: CT | B10: 199 | C10: 15 | D10: Bolsa Tecnología y Telecomunicaciones FI | E10: 44476.939 | F10: 36841 | G10: 13.039504 | H10: 22.99204 | I10: 765.3691 | J10: 357.9712
A11: V | B11: 1229 | E11: 44844.784 | G11: 12.534 | I11: 765.3691 | J11: =J10/I10*I11 -> 357.9712 | K11: ='Orig Vendes Reals 29'!K3 -> 765.3691 | L11: =J10/I10*K11 -> 357.9712
A12: CT | B12: 201 | C12: 15 | D12: Bolsa Tecnología y Telecomunicaciones FI | E12: 44477.939 | F12: 36841 | G12: 1904.1616 | H12: 22.99204 | I12: 4.6419 | J12: 321.6689
A13: CT | B13: 1231 | C13: 15 | D13: Bolsa Tecnología y Telecomunicaciones FI | E13: 44861.454 | F13: 36841 | G13: 10.282473 | H13: 22.99204 | I13: 810.6965 | J13: 321.6689
A14: CT | B14: 1239 | C14: 15 | D14: Bolsa Tecnología y Telecomunicaciones FI | E14: 44893.573 | F14: 36841 | G14: 433.54193 | H14: 22.99204 | I14: 18.6356 | J14: 321.6689
A15: V | B15: 1278 | E15: 45495.442 | G15: 457.7421 | I15: 18.636 | J15: =J14/I14*I15 -> 321.6758 | K15: ='Orig Vendes Reals 28'!K3 -> 18.6356 | L15: =J14/I14*K15 -> 321.6689

Sheet 27-Global Tech
D1: Parts | E1: PU | F1: Brut | H1: Saldo Parts | I1: Venudes | J1: En cartera | K1: Import compra cartera | L1: PiG venudes | M1: PiG cartera | N1: PiG Total
A2: 173 | B2: Traspàs C | C2: 43525 | D2: 1778.69 | E2: 17.05 | F2: =D2*E2 -> 30326.665 | H2: =D2 -> 1778.69 | I2: =SUM(D3:D8)+D11 -> 1642.08 | J2: =D2-I2 -> 136.61 | K2: =E2*J2 -> 2329.2005 | L2: =(SUM(F3:F8)+F11)-I2*E2 -> 28023.202 | M2: =(E12-E2)*J2 -> 4027.2628 | N2: =L2+M2 -> 32050.465
A3: 198 | B3: Traspàs V | C3: 44470 | D3: 287.03 | E3: 34.77 | F3: =D3*E3 -> 9980.0331 | H3: =H2-D3 -> 1491.66
A4: 200 | B4: Traspàs V | C4: 44473 | D4: 287.03 | E4: 34.27 | F4: =D4*E4 -> 9836.5181 | H4: =H3-D4 -> 1204.63
A5: 216 | B5: Traspàs V | C5: 44720 | D5: 296.82 | E5: 33.91 | F5: =D5*E5 -> 10065.166 | H5: =H4-D5 -> 907.81
A6: 1227 | B6: Traspàs V | C6: 44831 | D6: 308.74 | E6: 32.26 | F6: =D6*E6 -> 9959.9524 | H6: =H5-D6 -> 599.07
A7: 1247 | B7: Traspàs V | C7: 45028 | D7: 172.46 | E7: 34.47 | F7: =D7*E7 -> 5944.6962 | H7: =H6-D7 -> 426.61
A8: 1251 | B8: Venda | C8: 45054 | D8: 270 | E8: 34.29 | F8: =D8*E8 -> 9258.3 | H8: =H7-D8 -> 156.61
A9: 1273 | B9: Traspàs C | C9: 45356 | D9: 266.59 | E9: 44.920826 | F9: =D9*E9 -> 11975.443 | H9: =H8+D9 -> 423.2 | J9: =D9 -> 266.59 | K9: =E9*J9 -> 11975.443 | L9: 0 | M9: =(E$12-E9)*J9 -> 428.9897 | N9: =L9+M9 -> 428.9897
A10: 1275 | B10: Traspàs C | C10: 45478 | D10: 301.27 | E10: 49.4401 | F10: =D10*E10 -> 14894.819 | H10: =H9+D10 -> 724.47 | J10: =D10 -> 301.27 | K10: =E10*J10 -> 14894.819 | L10: 0 | M10: =(E$12-E10)*J10 -> -876.72589 | N10: =L10+M10 -> -876.72589
A11: 1279 | B11: Traspàs V | C11: 45495 | D11: 20 | E11: 48.8 | F11: =D11*E11 -> 976 | H11: =H10-D11 -> 704.47
B12: En cartera | D12: =H11 -> 704.47 | E12: 46.53 | F12: =D12*E12 -> 32778.989 | J12: =SUM(J2:J11) -> 704.47
J13: Totals ---> | K13: =SUM(K2:K12) -> 29199.462 | L13: =SUM(L2:L12) -> 28023.202 | M13: =SUM(M2:M12) -> 3579.5266 | N13: =SUM(N2:N12) -> 31602.729
E14: PiG venda 1251 | F14: =D8*(E8-E2) -> 4654.8
E15: PiG venda 1279 | F15: =D11*(E11-E2) -> 635 | I15: 173 | J15: =J2*E2 -> 2329.2005
I16: 1273 | J16: =J9*E9 -> 11975.443 | L16: 238.3668 | M16: 28.2232 | N16: =+L16+M16 -> 266.59
I17: 1275 | J17: =J10*E10 -> 14894.819 | L17: 97.8492 | M17: 20.5583 | N17: 182.8625 | O17: =SUM(L17:N17) -> 301.27
J18: =SUM(J15:J17) -> 29199.462
A20: 1042-DWS Floating Rate Notes LC
A21: 1263 | B21: Compra | C21: 45209 | D21: 116.8907 | E21: 85.55 | F21: 10000 | J21: =D21 -> 116.8907 | M21: =(E22-E21)*J21 -> 439.50903
E22: 89.31
A23: 1043-Global Technology A-Acc-USD H
A24: 1280 | B24: Traspàs C | C24: 45495 | D24: 20.32 | E24: 48.0202 | F24: 975.77 | J24: =D24 -> 20.32 | M24: =(E25-E24)*J24 -> -49.60112
E25: 45.5792
A26: Arcelor | I26: Desp | N26: Amb Desp
A27: 1286 | B27: Compra | C27: 45539 | D27: 50 | E27: 19.97 | F27: 998.5 | G27: 1005.78 | I27: 7.28 | J27: =D27 -> 50 | M27: =(E28-E27)*J27 -> 27 | N27: =M27-I27 -> 19.72
E28: 20.51
A29: Arcelor Trade
A30: 1288 | B30: Compra | C30: 45545 | D30: 1000 | E30: 19.9 | F30: 19900 | G30: 19901 | I30: 1 | J30: =D30 -> 1000 | M30: =(E31-E30)*J30 -> 614 | N30: =M30-I30 -> 613
E31: 20.514
E33: Venda | F33: 11025.76
E34: Compra | F34: 9979.52
F35: =+F33-F34 -> 1046.24
E37: 469.02
E38: 482.6
E39: =+E37-E38 -> -13.58

Sheet Orig Vendes Reals 27
A1: Mov | B1: Id | C1: Id Orig | D1: Nom Fons Orig | E1: Data Compra Venda | F1: Data Orig Compra | G1: PU | H1: PU Orig | I1: Parts | J1: Parts Orig | K1: Parts Util | L1: Parts Orig Ut | M1: Parts en cartera | N1: Parts orig en cartera | O1: Import Orig venda real | P1: Import orig en cartera | Q1: Pig Origen venda real | R1: PiG Orig en cartera | S1: PiG Total
A2: CT | B2: 173 | C2: 15 | D2: Bolsa Tecnología y Telecomunicaciones FI | E2: 43525 | F2: 36841 | G2: 17.05 | H2: 22.99204 | I2: 544.952 | J2: 679.6401 | K2: =SUM(K3:K4) -> 544.952 | L2: 679.6401 | M2: =I2-K2 -> 0 | N2: =J2/I2*M2 -> 0 | O2: =H2*L2 -> 15626.312 | P2: =N2*H2 -> 0 | Q2: =SUM(O3:O4)-O2 -> 3321.6687 | R2: =M2*G$19-P2 -> 0 | S2: =Q2+R2 -> 3321.6687
A3: VT | B3: 198 | E3: 44470 | G3: 34.77 | I3: 287.03 | K3: =I3 -> 287.03 | O3: =K3*G3 -> 9980.0331
A4: VT | B4: 200 | E4: 44473 | G4: 34.77 | I4: 287.03 | K4: =I2-K3 -> 257.922 | O4: =K4*G4 -> 8967.9479
B5: 173 | C5: 16 | D5: Total Return N Acc €-H1 | E5: 43525 | F5: 41166 | G5: 17.05 | H5: 18.26 | I5: 1065.5911 | J5: 547.6451 | K5: =SUM(K6:K10) -> 1065.5911 | L5: =J5 -> 547.6451 | M5: =I5-K5 -> 0 | N5: =J5-L5 -> 0 | O5: =H5*L5 -> 9999.9995 | P5: =N5*H5 -> 0 | Q5: =SUM(O6:O10)-O5 -> 25844.6 | R5: =M5*G$19-P5 -> 0 | S5: =Q5+R5 -> 25844.6
A6: VT | B6: 200 | E6: 44473 | G6: 34.77 | I6: 287.03 | K6: =I6-K4 -> 29.108 | O6: =K6*G6 -> 1012.0852
A7: VT | B7: 216 | E7: 44720 | G7: 33.91 | I7: 296.82 | K7: =I7 -> 296.82 | O7: =K7*G7 -> 10065.166
A8: VT | B8: 1227 | E8: 44831 | G8: 32.26 | I8: 308.74 | K8: =I8 -> 308.74 | O8: =K8*G8 -> 9959.9524
A9: VT | B9: 1247 | E9: 45028 | G9: 34.47 | I9: 172.46 | K9: =I9 -> 172.46 | O9: =K9*G9 -> 5944.6962
A10: V | B10: 1251 | E10: 45054 | G10: 34.29 | I10: 270 | K10: =I5-SUM(K6:K9) -> 258.4631 | O10: =K10*G10 -> 8862.6997
A11: CT | B11: 173 | C11: 17 | D11: Total Return N Acc €-H1 | E11: 43525 | F11: 41377 | G11: 17.05 | H11: 19.789998 | I11: 168.147 | J11: 86.4482 | K11: =K12 -> 11.5369 | L11: =J11/I11*K11 -> 5.9313829 | M11: =I11-K11 -> 156.6101 | N11: =J11-L11 -> 80.516817 | O11: =H11*L11 -> 117.38206 | P11: =N11*H11 -> 1593.4277 | Q11: =O12-O11 -> 278.21824 | R11: =M11*G$19-P11 -> 5693.6403 | S11: =Q11+R11 -> 5971.8585
A12: V | B12: 1251 | E12: 45054 | G12: 34.29 | I12: 270 | K12: =I12-K10 -> 11.5369 | O12: =K12*G12 -> 395.6003
A13: CT | B13: 1275 | C13: 16 | D13: Total Return N Acc €-H1 | E13: 45478 | F13: 41166 | G13: 49.4401 | H13: 18.26 | I13: 97.849 | J13: 88.6333 | K13: =I14 -> 20 | L13: =J13/I13*K13 -> 18.116343 | M13: =I13-K13 -> 77.849 | N13: =J13-L13 -> 70.516957 | O13: =H13*L13 -> 330.80441 | P13: =N13*H13 -> 1287.6396 | Q13: =O14-O13 -> 645.19559 | R13: =M13*G$19-P13 -> 2334.6743 | S13: =Q13+R13 -> 2979.8699
A14: VT | B14: 1279 | E14: 45495 | G14: 48.8 | I14: 20 | K14: =I14 -> 20 | O14: =K14*G14 -> 976
A15: CT | B15: 1273 | C15: 17 | D15: Total Return N Acc €-H1 | E15: 45356 | F15: 41377 | G15: 44.9208 | H15: 19.789998 | I15: 238.367 | J15: 264.6467 | K15: 0 | L15: =J15/I15*K15 -> 0 | M15: =I15-K15 -> 238.367 | N15: =J15-L15 -> 264.6467 | O15: =H15*L15 -> 0 | P15: =N15*H15 -> 5237.3578 | Q15: 0 | R15: =M15*G$19-P15 -> 5853.8588 | S15: =Q15+R15 -> 5853.8588
A16: CT | B16: 1273 | C16: 27 | D16: Optimal Income A-H Grs Acc Hdg EUR | E16: 45356 | F16: 41521 | G16: 44.9208 | H16: 17.093262 | I16: 28.223 | J16: 45.4774 | K16: 0 | L16: =J16/I16*K16 -> 0 | M16: =I16-K16 -> 28.223 | N16: =J16-L16 -> 45.4774 | O16: =H16*L16 -> 0 | P16: =N16*H16 -> 777.3571 | Q16: 0 | R16: =M16*G$19-P16 -> 535.85909 | S16: =Q16+R16 -> 535.85909
A17: CT | B17: 1275 | C17: 1253 | D17: Pictet-short-term Money Market Chf R | E17: 45478 | F17: 45061 | G17: 49.4401 | H17: 118.91483 | I17: 20.558 | J17: 8.4096 | K17: 0 | L17: =J17/I17*K17 -> 0 | M17: =I17-K17 -> 20.558 | N17: =J17-L17 -> 8.4096 | O17: =H17*L17 -> 0 | P17: =N17*H17 -> 1000.0261 | Q17: 0 | R17: =M17*G$19-P17 -> -43.462389 | S17: =Q17+R17 -> -43.462389
A18: CT | B18: 1275 | C18: 1254 | D18: Pictet-short-term Money Market Chf R | E18: 45478 | F18: 45069 | G18: 49.4401 | H18: 120.31804 | I18: 182.863 | J18: 74.8017 | K18: 0 | L18: =J18/I18*K18 -> 0 | M18: =I18-K18 -> 182.863 | N18: =J18-L18 -> 74.8017 | O18: =H18*L18 -> 0 | P18: =N18*H18 -> 8999.994 | Q18: 0 | R18: =M18*G$19-P18 -> -491.3786 | S18: =Q18+R18 -> -491.3786
G19: ='27-Global Tech'!E12 -> 46.53 | L19: En cartera | M19: =SUM(M2:M18) -> 704.4701 | P19: =SUM(P2:P18) -> 18895.802 | Q19: =SUM(Q2:Q18) -> 30089.683 | R19: =SUM(R2:R18) -> 13883.191 | S19: =SUM(S2:S18) -> 43972.874
R20: 13883.187
D21: Venda 1251 | R21: =+R19-R20 -> 0.0044662892
C22: Id Orig | D22: Parts comp orig | E22: Imp comp Orig
C23: 16 | D23: =J5/I5*K10 -> 132.83336 | E23: =D23*H5 -> 2425.5372
C24: 17 | D24: =J11/I11*K12 -> 5.9313829 | E24: =D24*H11 -> 117.38206
D25: Import compra | E25: =SUM(E23:E24) -> 2542.9193
D26: Import Venda | E26: ='27-Global Tech'!F8 -> 9258.3
D27: PiG 1251 | E27: =E26-E25 -> 6715.3807
D30: Compra 173
D31: PiG vendes | E31: =SUM(Q2:Q11) -> 29444.487
D32: PiG Cartera | E32: =SUM(R2:R11) -> 5693.6403
D33: Total | E33: =SUM(E31:E32) -> 35138.127

Sheet 28-Euro Fund
D1: Parts | E1: PU | I1: Part cartera | J1: PiG | K1: Import comp cartera | L1: PiG Cartera
A2: 197 | B2: Traspàs C | C2: 44473 | D2: 24.54 | E2: 435.1019 | G2: =D2 -> 24.54 | H2: =-D2*E2 -> -10677.401 | I2: =D2-D9 -> 5.904 | J2: =(E9-E2)*D9 -> 421.92277 | K2: =I2*E2 -> 2568.8416 | L2: =(E$10-E2)*I2 -> 148.85224
A3: 203 | B3: Traspàs C | C3: 44496 | D3: 34.724 | E3: 434.9468 | G3: =G2+D3 -> 59.264 | H3: =-D3*E3 -> -15103.093 | I3: =D3 -> 34.724 | K3: =I3*E3 -> 15103.093 | L3: =(E$10-E3)*I3 -> 880.85065
A4: 205 | B4: Traspàs C | C4: 44524 | D4: 46.266 | E4: 434.7577 | G4: =G3+D4 -> 105.53 | H4: =-D4*E4 -> -20114.5 | I4: =D4 -> 46.266 | K4: =I4*E4 -> 20114.5 | L4: =(E$10-E4)*I4 -> 1182.3878
A5: 217 | B5: Traspàs C | C5: 44725 | D5: 23.23 | E5: 433.2831 | G5: =G4+D5 -> 128.76 | H5: =-D5*E5 -> -10065.166 | I5: =D5 -> 23.23 | K5: =I5*E5 -> 10065.166 | L5: =(E$10-E5)*I5 -> 627.92781
A6: 1235 | B6: Traspàs C | C6: 44893 | D6: 21.81 | E6: 433.5199 | G6: =G5+D6 -> 150.57 | H6: =-D6*E6 -> -9455.069 | I6: =D6 -> 21.81 | K6: =I6*E6 -> 9455.069 | L6: =(E$10-E6)*I6 -> 584.37932
A7: 1239 | B7: Traspàs C | C7: 44893 | D7: 18.636 | E7: 433.5419 | G7: =G6+D7 -> 169.206 | H7: =-D7*E7 -> -8079.4868 | I7: =D7 -> 18.636 | K7: =I7*E7 -> 8079.4868 | L7: =(E$10-E7)*I7 -> 498.92486
A8: 1241 | B8: Traspàs C | C8: 44939 | D8: 5.872 | E8: 434.4509 | G8: =G7+D8 -> 175.078 | H8: =-D8*E8 -> -2551.0957 | I8: =D8 -> 5.872 | K8: =I8*E8 -> 2551.0957 | L8: =(E$10-E8)*I8 -> 151.86812
A9: 1278 | B9: Venda | C9: 45495 | D9: 18.636 | E9: 457.7421 | G9: =G8-D9 -> 156.442 | H9: =D9*E9 -> 8530.4818
B10: Cartera | D10: =G9 -> 156.442 | E10: 460.314 | H10: =D10*E10 -> 72012.443
E11: 460.0644 | J11: =SUM(J2:J9) -> 421.92277 | K11: =SUM(K2:K9) -> 67937.252 | L11: =SUM(L2:L9) -> 4075.1908
K12: PiG Total | L12: =+J11+L11 -> 4497.1135
L14: 4075.19

Sheet Orig Vendes Reals 28
A1: Mov | B1: Id | C1: Id Orig | D1: Nom Fons Orig | E1: Data Compra Venda | F1: Data Orig Compra | G1: PU | H1: PU Orig | I1: Parts | J1: Parts Orig | K1: Parts Util | L1: Parts Orig Ut | M1: Parts en cartera | N1: Parts orig en cartera | O1: Import Orig venda real | P1: Import Orig en cartera | Q1: Pig Origen venda real | R1: PiG Orig en cartera | S1: Pig SelfBank | T1: PiG Total
A2: CT | B2: 1239 | C2: 15 | D2: Bolsa Tecnología y Telecomunicaciones FI | E2: 44893.573 | F2: 36841 | G2: 433.54193 | H2: 22.99204 | I2: 18.6356 | J2: 321.6689 | K2: =K3 -> 18.6356 | L2: =J2/I2*K2 -> 321.6689 | M2: =I2-K2 -> 0 | N2: =J2-L2 -> 0 | O2: =$H2*L2 -> 7395.8242 | P2: =$H2*N2 -> 0 | Q2: =K3*G3-O2 -> 1134.4745 | R2: =M2*G$16-P2 -> 0 | S2: =S$3/I3*I2 -> 1836.6006 | T2: =Q2+R2 -> 1134.4745
A3: V | B3: 1278 | E3: 45495.442 | G3: 457.7421 | I3: 18.636 | K3: =I2 -> 18.6356 | S3: 1836.64
A4: CT | B4: 217 | C4: 16 | D4: Total Return N Acc €-H1 | E4: 44725.295 | F4: 41166 | G4: 433.28309 | H4: 18.26 | I4: 23.23 | J4: 152.5463 | K4: =K5 -> 0.0004 | L4: =J4/I4*K4 -> 0.002626712 | M4: =I4-K4 -> 23.2296 | N4: =J4-L4 -> 152.54367 | O4: =$H4*L4 -> 0.047963761 | P4: =$H4*N4 -> 2785.4475 | Q4: =K5*G5-O4 -> 0.13513308 | R4: =M4*G$16-P4 -> 7907.4626 | S4: =S$3/I5*I4 -> 2289.394 | T4: =Q4+R4 -> 7907.5978
A5: V | B5: 1278 | E5: 45495.442 | G5: 457.7421 | I5: 18.636 | K5: =I6 -> 0.0004 | S5: 1836.64
A6: CT | B6: 1239 | C6: 16 | D6: Total Return N Acc €-H1 | E6: 44893.573 | F6: 41166 | G6: 433.54193 | H6: 18.26 | I6: 0.0004 | J6: 0.0029
A7: CT | B7: 1241 | C7: 16 | D7: Total Return N Acc €-H1 | E7: 44939.567 | F7: 41166 | G7: 434.45089 | H7: 18.26 | I7: 2.0113 | J7: 14.9568
A8: CT | B8: 1235 | C8: 16 | D8: Total Return N Acc €-H1 | E8: 44893.559 | F8: 41166 | G8: 433.51992 | H8: 18.26 | I8: 21.81 | J8: 158.6724
A9: CT | B9: 197 | C9: 17 | D9: Total Return N Acc €-H1 | E9: 44473.585 | F9: 41377 | G9: 435.10187 | H9: 19.789998 | I9: 24.54 | J9: 226.4851
A10: CT | B10: 1241 | C10: 17 | D10: Total Return N Acc €-H1 | E10: 44939.567 | F10: 41377 | G10: 434.45089 | H10: 19.789998 | I10: 1.1525 | J10: 18.2224
A11: CT | B11: 205 | C11: 17 | D11: Total Return N Acc €-H1 | E11: 44524.517 | F11: 41377 | G11: 434.75771 | H11: 19.789998 | I11: 46.266 | J11: 396.3489
A12: CT | B12: 203 | C12: 7 | D12: Biotechnology C USD Acc | E12: 44496.481 | F12: 41492 | G12: 434.94679 | H12: 250.44123 | I12: 29.761 | J12: 22.006
A13: CT | B13: 1241 | C13: 27 | D13: Optimal Income A-H Grs Acc Hdg EUR | E13: 44939.567 | F13: 41521 | G13: 434.45089 | H13: 17.093262 | I13: 0.6438 | J13: 13.0237
A14: CT | B14: 203 | C14: 37 | D14: European Growth N Acc ? | E14: 44496.481 | F14: 41534 | G14: 434.94679 | H14: 13.029995 | I14: 4.963 | J14: 76.746
A15: CT | B15: 1241 | C15: 108 | D15: Trea Renta Fija Ahorro S FI | E15: 44939.567 | F15: 42387.493 | G15: 434.45089 | H15: 1860.4651 | I15: 2.0644 | J15: 0.5375
G16: ='28-Euro Fund'!E10 -> 460.314
E18: Venda 1278 segons SelfBank
E19: Data compra | F19: Parts | G19: Import
E20: 36871 | F20: 7.168 | G20: 3087.53
E21: 36889 | F21: 9.688 | G21: 3005.06
E22: 36913 | F22: 1.778 | G22: 601.01
E23: 41169 | F23: 0.002 | G23: 0.23
E24: Total | F24: =SUM(F20:F23) -> 18.636 | G24: =SUM(G20:G23) -> 6693.83
E25: Data venda | F25: Parts | G25: Import
E26: 45495 | F26: 18.636 | G26: 8530.48
F27: PiG | G27: =G26-G24 -> 1836.65
S35: =S$3/#REF!*G35 -> #REF!

Sheet 29-CS Corto Plazo
D1: Parts | E1: PU | F1: Brut
A2: 199 | B2: Traspàs C | C2: 44476 | D2: 765.3691 | E2: 13.0395 | F2: 9980.03
A3: 1229 | B3: Venda | C3: 44844 | D3: 765.3691 | E3: 12.534 | F3: 9593.14
E4: PiG | F4: =+F3-F2 -> -386.89

Sheet Orig Vendes Reals 29
A1: Mov | B1: Id | C1: Id Orig | D1: Nom Fons Orig | E1: Data Compra Venda | F1: Data Orig Compra | G1: PU | H1: PU Orig | I1: Parts | J1: Parts Orig | K1: Parts Util | L1: Parts Orig Ut | M1: Parts en cartera | N1: Parts orig en cartera | O1: Import Orig venda real | P1: Import Orig en cartera | Q1: Pig Origen venda real | R1: PiG Orig en cartera
A2: CT | B2: 199 | C2: 15 | D2: Bolsa Tecnología y Telecomunicaciones FI | E2: 44476.939 | F2: 36841 | G2: 433.54193 | H2: 22.99204 | I2: 765.3691 | J2: 357.9712 | K2: =K3 -> 765.3691 | L2: =J2/I2*K2 -> 357.9712 | M2: =I2-K2 -> 0 | N2: =J2-L2 -> 0 | O2: =$H2*L2 -> 8230.4881 | P2: =$H2*N2 -> 0 | Q2: =K3*G3-O2 -> 1362.6482
A3: V | B3: 1229 | E3: 44844.784 | G3: 12.534 | I3: 765.3691 | K3: =I3 -> 765.3691
G5: Prod | H5: Venudes en
G6: 29 | H6: Id: 1229 | K6: =J2 -> 357.9712
G7: 28 | H7: Id: 1278 | K7: 321.6689
H8: bbva | K8: =SUM(K6:K7) -> 679.6401
